README.md
setup.py
cybele/__init__.py
cybele/constants.py
cybele.egg-info/PKG-INFO
cybele.egg-info/SOURCES.txt
cybele.egg-info/dependency_links.txt
cybele.egg-info/entry_points.txt
cybele.egg-info/requires.txt
cybele.egg-info/top_level.txt
cybele/aes/__init__.py
cybele/aes/cipher.py
cybele/aes/exception.py
cybele/api/__init__.py
cybele/api/core.py
cybele/api/exceptions.py
cybele/api/utils.py
cybele/cli/__init__.py
cybele/cli/core.py
cybele/cli/utils.py
tests/__init__.py
tests/test_aes.py
tests/test_cli/__init__.py
tests/test_cli/test_utils.py
tests/test_core/__init__.py
tests/test_core/fixtures.py
tests/test_core/test_clipboard.py
tests/test_core/test_crud.py
tests/test_core/test_load_dump.py