Metadata-Version: 2.1
Name: cybele
Version: 0.3.7
Summary: cli password manager
Home-page: https://gitlab.com/dithyrambe/cybele
License: MIT
Platform: UNKNOWN
Classifier: Programming Language :: Python :: 3.6
